{
  "data": {
    "OpenMayaAnim": [
      "MAnimCurveClipboard",
      "MFnMotionPath",
      "MAnimCurveClipboardItem",
      "MFnAnimCurve",
      "MAnimCurveClipboardItemArray",
      "MFnKeyframeDeltaTangent",
      "MFnCharacter",
      "MFnIkSolver",
      "MAnimControl",
      "MFnKeyframeDeltaWeighted",
      "MFnKeyframeDelta",
      "MFnWireDeformer",
      "MFnKeyframeDeltaScale",
      "MFnSkinCluster",
      "MAnimUtil",
      "MFnBlendShapeDeformer",
      "MFnKeyframeDeltaBlockAddRemove",
      "MFnKeyframeDeltaMove",
      "MFnKeyframeDeltaInfType",
      "MFnClip",
      "MFnKeyframeDeltaBreakdown",
      "MItKeyframe",
      "MFnIkEffector",
      "MFnIkHandle",
      "MFnKeyframeDeltaAddRemove",
      "MFnLattice",
      "MFnWeightGeometryFilter",
      "MAnimCurveChange",
      "MAnimMessage",
      "MFnHikEffector",
      "MFnLatticeDeformer",
      "MFnIkJoint",
      "MFnGeometryFilter",
      "MIkSystem",
      "MIkHandleGroup"
    ],
    "OpenMayaRender": [
      "MRenderData",
      "MHwTextureManager",
      "MRenderView",
      "MVaryingParameter",
      "MSwatchRenderRegister",
      "MD3D9Renderer",
      "MFnRenderPass",
      "MDrawProcedureBase",
      "MGeometryData",
      "MVaryingParameterList",
      "MSwatchRenderBase",
      "MLightLinks",
      "MHwrCallback",
      "MGeometryList",
      "MRenderingInfo",
      "MRenderShadowData",
      "MRenderProfile",
      "MGeometryPrimitive",
      "MRenderCallback",
      "MGLFunctionTable",
      "MCommonRenderSettingsData",
      "MViewportRenderer",
      "MUniformParameterList",
      "MUniformParameter",
      "MFnImageSource",
      "MGeometryManager",
      "MRenderUtil",
      "MHardwareRenderer",
      "MFnRenderLayer"
    ],
    "OpenMayaMPx": [
      "MPxContextCommand",
      "MPxSurfaceShapeUI",
      "MPxModelEditorCommand",
      "MPx3dModelView",
      "MPxSkinCluster",
      "MPxEmitterNode",
      "MFnPlugin",
      "MPxImageFile",
      "MPxRepresentation",
      "MPxTransformationMatrix",
      "MPxLocatorNode",
      "MPxMayaAsciiFilter",
      "MPxAssembly",
      "MPxSpringNode",
      "MPxTransform",
      "MPxSelectionContext",
      "MPxHwShaderNode",
      "MPxConstraintCommand",
      "MPxManipContainer",
      "MPxManipulatorNode",
      "MPxMidiInputDevice",
      "MPxPolyTweakUVCommand",
      "MPxGlBuffer",
      "MPxParticleAttributeMapperNode",
      "MPxPolyTrg",
      "MPxPolyTweakUVInteractiveCommand",
      "MPxDeformerNode",
      "MPxTexContext",
      "MPxFileTranslator",
      "MaterialInputData",
      "MPxToolCommand",
      "MPxMayaAsciiFilterOutput",
      "MPxCacheFormat",
      "MPxObjectSet",
      "MPxNode",
      "MPxEditData",
      "MExternalContentInfoTable",
      "MPxCameraSet",
      "MPxAnimCurveInterpolator",
      "MPxBakeEngine",
      "MPxFluidEmitterNode",
      "MPxUITableControl",
      "MPxHardwareShader",
      "MPxFileResolver",
      "MPxCommand",
      "MPxFieldNode",
      "MPxContext",
      "MPxGeometryIterator",
      "MPxGeometryFilter",
      "MPxBlendShape",
      "MPxIkSolverNode",
      "MExternalContentLocationTable",
      "MPxComponentShape",
      "MPxData",
      "MPxMaterialInformation",
      "MPxAttributePatternFactory",
      "MPxControlCommand",
      "MPxDragAndDropBehavior",
      "MPxImagePlane",
      "MPxUIControl",
      "MPxRenderPassImpl",
      "MPxConstraint",
      "MPxSurfaceShape",
      "MPxGeometryData",
      "MPxMotionPathNode"
    ],
    "OpenMaya": [
      "MColorArray",
      "MItInstancer",
      "MFnContainerNode",
      "MPlugArray",
      "MItSurfaceCV",
      "MUuid",
      "MItMeshFaceVertex",
      "MFnPhongShader",
      "MFnTransform",
      "MNurbsIntersector",
      "MDataHandle",
      "MDGModifier",
      "MFnMatrixArrayData",
      "MFnPointLight",
      "MFnLambertShader",
      "MCommandResult",
      "MCameraSetMessage",
      "MItMeshPolygon",
      "MFnIntArrayData",
      "MModelMessage",
      "MFloatMatrix",
      "MFnUInt64ArrayData",
      "MGlobal",
      "MSyntax",
      "MSceneMessage",
      "MFnAmbientLight",
      "MCommandMessage",
      "MDagModifier",
      "MFnVectorArrayData",
      "MFnBlinnShader",
      "MObjectArray",
      "MVector",
      "MDagMessage",
      "MEvaluationNodeIterator",
      "MRampAttribute",
      "MRenderPassRegistry",
      "MAngle",
      "MFnNumericData",
      "MFnLight",
      "MEvaluationNode",
      "MFnNurbsCurve",
      "MFnStringArrayData",
      "MFnStringData",
      "MItDependencyNodes",
      "MFnMatrixData",
      "MPlane",
      "MTimerMessage",
      "MTesselationParams",
      "MFnVolumeLight",
      "MTime",
      "MFnUint64SingleIndexedComponent",
      "MEulerRotation",
      "MIteratorType",
      "MFnCamera",
      "MFnSet",
      "MItCurveCV",
      "MMeshSmoothOptions",
      "MStreamUtils",
      "MFnNurbsSurfaceData",
      "MObjectSetMessage",
      "MLockMessage",
      "MFnNurbsCurveData",
      "MFloatArray",
      "MItDag",
      "MParentingEdit",
      "MFileIO",
      "MArgList",
      "MPoint",
      "MDoubleArray",
      "MFnGenericAttribute",
      "MSpace",
      "MFnCompoundAttribute",
      "MUintArray",
      "MCacheFormatDescription",
      "MProfilingScope",
      "MFnAnisotropyShader",
      "MFnSubdData",
      "MFnLatticeData",
      "MProfiler",
      "MFnTypedAttribute",
      "MComputation",
      "MArgDatabase",
      "MImage",
      "MAttributePatternArray",
      "MMessageNode",
      "MRichSelection",
      "MFnMesh",
      "MFloatVectorArray",
      "MAttributeSpec",
      "MBoundingBox",
      "MFnFloatArrayData",
      "MItEdits",
      "MContainerMessage",
      "MArrayDataBuilder",
      "MFnDagNode",
      "MDGMessage",
      "MItSubdFace",
      "MFloatVector",
      "MMessage",
      "MURI",
      "MEvaluationManager",
      "MNamespace",
      "MPointArray",
      "MTimeArray",
      "MObject",
      "MFnComponentListData",
      "MTransformationMatrix",
      "MFnTripleIndexedComponent",
      "MArrayDataHandle",
      "MFnDirectionalLight",
      "MItSubdEdge",
      "MFnCameraSet",
      "MFnMessageAttribute",
      "MFnNonAmbientLight",
      "MMeshIntersector",
      "MRenderPassDef",
      "MAttributePattern",
      "MDagPath",
      "MFcurveEdit",
      "MSetAttrEdit",
      "MVectorArray",
      "MAttributeIndex",
      "MFnUnitAttribute",
      "MMatrixArray",
      "MFnDependencyNode",
      "MFloatPointArray",
      "MFnLayeredShader",
      "MItDependencyGraph",
      "MItSubdVertex",
      "MFnComponent",
      "MPolyMessage",
      "MUserData",
      "MEventMessage",
      "MFnSpotLight",
      "MFnReflectShader",
      "MMeshIsectAccelParams",
      "MDagPathArray",
      "MCallbackIdArray",
      "MNodeMessage",
      "MFnPhongEShader",
      "MFnLightDataAttribute",
      "MFnBase",
      "MFnPluginData",
      "MPointOnNurbs",
      "MFn",
      "MFnPartition",
      "MIntArray",
      "MWeight",
      "MObjectHandle",
      "MFnReference",
      "MEdit",
      "MFnEnumAttribute",
      "MFnDoubleIndexedComponent",
      "MMatrix",
      "MArgParser",
      "MFnNumericAttribute",
      "MUserEventMessage",
      "MTimer",
      "MItMeshVertex",
      "MFnAttribute",
      "MSelectionMask",
      "MFnSphereData",
      "MItMeshEdge",
      "MFnExpression",
      "MTypeId",
      "MQuaternion",
      "MFnGeometryData",
      "MFnPointArrayData",
      "MIffFile",
      "MFnSubdNames",
      "MAddRemoveAttrEdit",
      "MInt64Array",
      "MScriptUtil",
      "MUint64Array",
      "MConnectDisconnectAttrEdit",
      "MIffTag",
      "MFnDoubleArrayData",
      "MTrimBoundaryArray",
      "MFnArrayAttrsData",
      "MPlug",
      "MDataBlock",
      "MFloatPoint",
      "MFnAssembly",
      "MFileObject",
      "MDAGDrawOverrideInfo",
      "MDistance",
      "MFnNurbsSurface",
      "MAttributeSpecArray",
      "MFnSubd",
      "MNodeClass",
      "MSelectionList",
      "MFnMatrixAttribute",
      "MFnNonExtendedLight",
      "MItSelectionList",
      "MConditionMessage",
      "MFnData",
      "MDGContext",
      "MFnMeshData",
      "MImageFileInfo",
      "MFnAreaLight",
      "MItGeometry",
      "MColor",
      "MPointOnMesh",
      "MFnSingleIndexedComponent"
    ],
    "OpenMayaUI": [
      "MFnRotateManip",
      "MDrawRequest",
      "MFnToolContext",
      "MDrawTraversal",
      "MFeedbackLine",
      "MDrawData",
      "MGraphEditorInfo",
      "MDrawRequestQueue",
      "MTextureEditorDrawInfo",
      "MMaterialArray",
      "MFnDirectionManip",
      "MToolsInfo",
      "MFnDiscManip",
      "MUiMessage",
      "MFnFreePointTriadManip",
      "MExternalDropCallback",
      "MExternalDropData",
      "MDeviceChannel",
      "M3dView",
      "MSelectInfo",
      "MDrawInfo",
      "MDeviceState",
      "MFnToggleManip",
      "MHWShaderSwatchGenerator",
      "MManipData",
      "MObjectListFilter",
      "MQtUtil",
      "MFnPointOnCurveManip",
      "MFnCurveSegmentManip",
      "MFnPointOnSurfaceManip",
      "MFnStateManip",
      "MCursor",
      "MFnManip3D",
      "MMaterial",
      "MProgressWindow",
      "MEvent",
      "MFnScaleManip",
      "MFnDistanceManip",
      "MFnCircleSweepManip"
    ],
    "OpenMayaFX": [
      "MFnVortexField",
      "MFnInstancer",
      "MFnParticleSystem",
      "MDynamicsUtil",
      "MRenderLine",
      "MnRigid",
      "MFnRadialField",
      "MFnNObjectData",
      "MFnUniformField",
      "MFnDragField",
      "MnSolver",
      "MDynSweptTriangle",
      "MFnNIdData",
      "MFnFluid",
      "MnCloth",
      "MFnField",
      "MRenderLineArray",
      "MnObject",
      "MFnGravityField",
      "MDynSweptLine",
      "MFnVolumeAxisField",
      "MnParticle",
      "MFnTurbulenceField",
      "MHairSystem",
      "MFnDynSweptGeometryData",
      "MFnPfxGeometry",
      "MFnNewtonField",
      "MFnAirField"
    ]
  },
  "all": [
    "MAnimCurveClipboard",
    "MFnMotionPath",
    "MAnimCurveClipboardItem",
    "MFnAnimCurve",
    "MAnimCurveClipboardItemArray",
    "MFnKeyframeDeltaTangent",
    "MFnCharacter",
    "MFnIkSolver",
    "MAnimControl",
    "MFnKeyframeDeltaWeighted",
    "MFnKeyframeDelta",
    "MFnWireDeformer",
    "MFnKeyframeDeltaScale",
    "MFnSkinCluster",
    "MAnimUtil",
    "MFnBlendShapeDeformer",
    "MFnKeyframeDeltaBlockAddRemove",
    "MFnKeyframeDeltaMove",
    "MFnKeyframeDeltaInfType",
    "MFnClip",
    "MFnKeyframeDeltaBreakdown",
    "MItKeyframe",
    "MFnIkEffector",
    "MFnIkHandle",
    "MFnKeyframeDeltaAddRemove",
    "MFnLattice",
    "MFnWeightGeometryFilter",
    "MAnimCurveChange",
    "MAnimMessage",
    "MFnHikEffector",
    "MFnLatticeDeformer",
    "MFnIkJoint",
    "MFnGeometryFilter",
    "MIkSystem",
    "MIkHandleGroup",
    "MRenderData",
    "MHwTextureManager",
    "MRenderView",
    "MVaryingParameter",
    "MSwatchRenderRegister",
    "MD3D9Renderer",
    "MFnRenderPass",
    "MDrawProcedureBase",
    "MGeometryData",
    "MVaryingParameterList",
    "MSwatchRenderBase",
    "MLightLinks",
    "MHwrCallback",
    "MGeometryList",
    "MRenderingInfo",
    "MRenderShadowData",
    "MRenderProfile",
    "MGeometryPrimitive",
    "MRenderCallback",
    "MGLFunctionTable",
    "MCommonRenderSettingsData",
    "MViewportRenderer",
    "MUniformParameterList",
    "MUniformParameter",
    "MFnImageSource",
    "MGeometryManager",
    "MRenderUtil",
    "MHardwareRenderer",
    "MFnRenderLayer",
    "MPxContextCommand",
    "MPxSurfaceShapeUI",
    "MPxModelEditorCommand",
    "MPx3dModelView",
    "MPxSkinCluster",
    "MPxEmitterNode",
    "MFnPlugin",
    "MPxImageFile",
    "MPxRepresentation",
    "MPxTransformationMatrix",
    "MPxLocatorNode",
    "MPxMayaAsciiFilter",
    "MPxAssembly",
    "MPxSpringNode",
    "MPxTransform",
    "MPxSelectionContext",
    "MPxHwShaderNode",
    "MPxConstraintCommand",
    "MPxManipContainer",
    "MPxManipulatorNode",
    "MPxMidiInputDevice",
    "MPxPolyTweakUVCommand",
    "MPxGlBuffer",
    "MPxParticleAttributeMapperNode",
    "MPxPolyTrg",
    "MPxPolyTweakUVInteractiveCommand",
    "MPxDeformerNode",
    "MPxTexContext",
    "MPxFileTranslator",
    "MaterialInputData",
    "MPxToolCommand",
    "MPxMayaAsciiFilterOutput",
    "MPxCacheFormat",
    "MPxObjectSet",
    "MPxNode",
    "MPxEditData",
    "MExternalContentInfoTable",
    "MPxCameraSet",
    "MPxAnimCurveInterpolator",
    "MPxBakeEngine",
    "MPxFluidEmitterNode",
    "MPxUITableControl",
    "MPxHardwareShader",
    "MPxFileResolver",
    "MPxCommand",
    "MPxFieldNode",
    "MPxContext",
    "MPxGeometryIterator",
    "MPxGeometryFilter",
    "MPxBlendShape",
    "MPxIkSolverNode",
    "MExternalContentLocationTable",
    "MPxComponentShape",
    "MPxData",
    "MPxMaterialInformation",
    "MPxAttributePatternFactory",
    "MPxControlCommand",
    "MPxDragAndDropBehavior",
    "MPxImagePlane",
    "MPxUIControl",
    "MPxRenderPassImpl",
    "MPxConstraint",
    "MPxSurfaceShape",
    "MPxGeometryData",
    "MPxMotionPathNode",
    "MColorArray",
    "MItInstancer",
    "MFnContainerNode",
    "MPlugArray",
    "MItSurfaceCV",
    "MUuid",
    "MItMeshFaceVertex",
    "MFnPhongShader",
    "MFnTransform",
    "MNurbsIntersector",
    "MDataHandle",
    "MDGModifier",
    "MFnMatrixArrayData",
    "MFnPointLight",
    "MFnLambertShader",
    "MCommandResult",
    "MCameraSetMessage",
    "MItMeshPolygon",
    "MFnIntArrayData",
    "MModelMessage",
    "MFloatMatrix",
    "MFnUInt64ArrayData",
    "MGlobal",
    "MSyntax",
    "MSceneMessage",
    "MFnAmbientLight",
    "MCommandMessage",
    "MDagModifier",
    "MFnVectorArrayData",
    "MFnBlinnShader",
    "MObjectArray",
    "MVector",
    "MDagMessage",
    "MEvaluationNodeIterator",
    "MRampAttribute",
    "MRenderPassRegistry",
    "MAngle",
    "MFnNumericData",
    "MFnLight",
    "MEvaluationNode",
    "MFnNurbsCurve",
    "MFnStringArrayData",
    "MFnStringData",
    "MItDependencyNodes",
    "MFnMatrixData",
    "MPlane",
    "MTimerMessage",
    "MTesselationParams",
    "MFnVolumeLight",
    "MTime",
    "MFnUint64SingleIndexedComponent",
    "MEulerRotation",
    "MIteratorType",
    "MFnCamera",
    "MFnSet",
    "MItCurveCV",
    "MMeshSmoothOptions",
    "MStreamUtils",
    "MFnNurbsSurfaceData",
    "MObjectSetMessage",
    "MLockMessage",
    "MFnNurbsCurveData",
    "MFloatArray",
    "MItDag",
    "MParentingEdit",
    "MFileIO",
    "MArgList",
    "MPoint",
    "MDoubleArray",
    "MFnGenericAttribute",
    "MSpace",
    "MFnCompoundAttribute",
    "MUintArray",
    "MCacheFormatDescription",
    "MProfilingScope",
    "MFnAnisotropyShader",
    "MFnSubdData",
    "MFnLatticeData",
    "MProfiler",
    "MFnTypedAttribute",
    "MComputation",
    "MArgDatabase",
    "MImage",
    "MAttributePatternArray",
    "MMessageNode",
    "MRichSelection",
    "MFnMesh",
    "MFloatVectorArray",
    "MAttributeSpec",
    "MBoundingBox",
    "MFnFloatArrayData",
    "MItEdits",
    "MContainerMessage",
    "MArrayDataBuilder",
    "MFnDagNode",
    "MDGMessage",
    "MItSubdFace",
    "MFloatVector",
    "MMessage",
    "MURI",
    "MEvaluationManager",
    "MNamespace",
    "MPointArray",
    "MTimeArray",
    "MObject",
    "MFnComponentListData",
    "MTransformationMatrix",
    "MFnTripleIndexedComponent",
    "MArrayDataHandle",
    "MFnDirectionalLight",
    "MItSubdEdge",
    "MFnCameraSet",
    "MFnMessageAttribute",
    "MFnNonAmbientLight",
    "MMeshIntersector",
    "MRenderPassDef",
    "MAttributePattern",
    "MDagPath",
    "MFcurveEdit",
    "MSetAttrEdit",
    "MVectorArray",
    "MAttributeIndex",
    "MFnUnitAttribute",
    "MMatrixArray",
    "MFnDependencyNode",
    "MFloatPointArray",
    "MFnLayeredShader",
    "MItDependencyGraph",
    "MItSubdVertex",
    "MFnComponent",
    "MPolyMessage",
    "MUserData",
    "MEventMessage",
    "MFnSpotLight",
    "MFnReflectShader",
    "MMeshIsectAccelParams",
    "MDagPathArray",
    "MCallbackIdArray",
    "MNodeMessage",
    "MFnPhongEShader",
    "MFnLightDataAttribute",
    "MFnBase",
    "MFnPluginData",
    "MPointOnNurbs",
    "MFn",
    "MFnPartition",
    "MIntArray",
    "MWeight",
    "MObjectHandle",
    "MFnReference",
    "MEdit",
    "MFnEnumAttribute",
    "MFnDoubleIndexedComponent",
    "MMatrix",
    "MArgParser",
    "MFnNumericAttribute",
    "MUserEventMessage",
    "MTimer",
    "MItMeshVertex",
    "MFnAttribute",
    "MSelectionMask",
    "MFnSphereData",
    "MItMeshEdge",
    "MFnExpression",
    "MTypeId",
    "MQuaternion",
    "MFnGeometryData",
    "MFnPointArrayData",
    "MIffFile",
    "MFnSubdNames",
    "MAddRemoveAttrEdit",
    "MInt64Array",
    "MScriptUtil",
    "MUint64Array",
    "MConnectDisconnectAttrEdit",
    "MIffTag",
    "MFnDoubleArrayData",
    "MTrimBoundaryArray",
    "MFnArrayAttrsData",
    "MPlug",
    "MDataBlock",
    "MFloatPoint",
    "MFnAssembly",
    "MFileObject",
    "MDAGDrawOverrideInfo",
    "MDistance",
    "MFnNurbsSurface",
    "MAttributeSpecArray",
    "MFnSubd",
    "MNodeClass",
    "MSelectionList",
    "MFnMatrixAttribute",
    "MFnNonExtendedLight",
    "MItSelectionList",
    "MConditionMessage",
    "MFnData",
    "MDGContext",
    "MFnMeshData",
    "MImageFileInfo",
    "MFnAreaLight",
    "MItGeometry",
    "MColor",
    "MPointOnMesh",
    "MFnSingleIndexedComponent",
    "MFnRotateManip",
    "MDrawRequest",
    "MFnToolContext",
    "MDrawTraversal",
    "MFeedbackLine",
    "MDrawData",
    "MGraphEditorInfo",
    "MDrawRequestQueue",
    "MTextureEditorDrawInfo",
    "MMaterialArray",
    "MFnDirectionManip",
    "MToolsInfo",
    "MFnDiscManip",
    "MUiMessage",
    "MFnFreePointTriadManip",
    "MExternalDropCallback",
    "MExternalDropData",
    "MDeviceChannel",
    "M3dView",
    "MSelectInfo",
    "MDrawInfo",
    "MDeviceState",
    "MFnToggleManip",
    "MHWShaderSwatchGenerator",
    "MManipData",
    "MObjectListFilter",
    "MQtUtil",
    "MFnPointOnCurveManip",
    "MFnCurveSegmentManip",
    "MFnPointOnSurfaceManip",
    "MFnStateManip",
    "MCursor",
    "MFnManip3D",
    "MMaterial",
    "MProgressWindow",
    "MEvent",
    "MFnScaleManip",
    "MFnDistanceManip",
    "MFnCircleSweepManip",
    "MFnVortexField",
    "MFnInstancer",
    "MFnParticleSystem",
    "MDynamicsUtil",
    "MRenderLine",
    "MnRigid",
    "MFnRadialField",
    "MFnNObjectData",
    "MFnUniformField",
    "MFnDragField",
    "MnSolver",
    "MDynSweptTriangle",
    "MFnNIdData",
    "MFnFluid",
    "MnCloth",
    "MFnField",
    "MRenderLineArray",
    "MnObject",
    "MFnGravityField",
    "MDynSweptLine",
    "MFnVolumeAxisField",
    "MnParticle",
    "MFnTurbulenceField",
    "MHairSystem",
    "MFnDynSweptGeometryData",
    "MFnPfxGeometry",
    "MFnNewtonField",
    "MFnAirField"
  ]
}